{
  "name": "IconEllipses",
  "library": "terra-icon",
  "display": "Ellipses Icon",
  "description": "Ellipses Icon",
  "import_from": "terra-icon/lib/icon/IconEllipses",
  "group": "Atoms::Icons",
  "properties": {
    "isBidi": {
      "type": "Bool"
    },
    "isSpin": {
      "type": "Bool"
    },
    "focusable": {
      "type": "Bool"
    },
    "height": {
      "type": "String",
      "form_type": "DelayedInput",
      "default": "1em"
    },
    "width": {
      "type": "String",
      "form_type": "DelayedInput",
      "default": "1em"
    },
    "ariaLabel": {
      "type": "String"
    }
  }
}