{
  "name": "Toggle",
  "library": "terra-toggle",
  "display": "Toggle",
  "description": "A disclosure mechanism for showing and hiding content in an animated fashion",
  "group": "Molecules::Other",
  "documentation": "http://engineering.cerner.com/terra-ui/#/components/terra-toggle/toggle",
  "properties": {
    "isOpen": {
      "type": "Bool",
      "default": true,
      "display": "Open"
    },
    "isAnimated": {
      "type": "Bool",
      "display": "Animated"
    },
    "children": {
      "type": "Array",
      "schema": {
        "type": "Component"
      }
    }
  }
}
